{
  "project_info": {
    "project_number": "1059752600529",
    "firebase_url": "https://erevu-d7b6e.firebaseio.com",
    "project_id": "erevu-d7b6e",
    "storage_bucket": "erevu-d7b6e.appspot.com"
  },
  "client": [
    {
      "client_info": {
        "mobilesdk_app_id": "1:1059752600529:android:6beeeb5d46a1c14e",
        "android_client_info": {
          "package_name": "com.erevu.erevu"
        }
      },
      "oauth_client": [
        {
          "client_id": "1059752600529-ugiau897fobn70pgrtkaph1igns26gli.apps.googleusercontent.com",
          "client_type": 3
        }
      ],
      "api_key": [
        {
          "current_key": "AIzaSyCf211l7AxbtzDohS5wBt8xAsIiyUyY62M"
        }
      ],
      "services": {
        "analytics_service": {
          "status": 1
        },
        "appinvite_service": {
          "status": 1,
          "other_platform_oauth_client": []
        },
        "ads_service": {
          "status": 2
        }
      }
    }
  ],
  "configuration_version": "1"
}